hamplots/__init__.py
hamplots/analysers.py
hamplots/datasources.py
hamplots/runner.py
hamplots-1.1.6.dist-info/licenses/LICENSE
scraps/all file reader.py
scraps/demo_minimal_spots_to_file.py
scraps/demo_simple_spots_to_file.py
scraps/demo_spots_to_plots.py
scraps/geo.py
scraps/loadWebsdr.py
scraps/minimal_pskr_mqtt_listener.py
scraps/pcolor test.py
scraps/str_to_epoch.py
hamplots-1.1.6.dist-info/METADATA
hamplots-1.1.6.dist-info/WHEEL
hamplots-1.1.6.dist-info/entry_points.txt
hamplots-1.1.6.dist-info/top_level.txt
hamplots-1.1.6.dist-info/RECORD
