Metadata-Version: 2.4
Name: hamplots
Version: 1.1.6
Summary: Realtime plots for ham radio band conditions
Author-email: G1OJS <g1ojs@yahoo.com>
License-Expression: MIT
Project-URL: Homepage, https://github.com/G1OJS/hamplots
Project-URL: Issues, https://github.com/G1OJS/hamplots/issues
Requires-Python: >=3.10
License-File: LICENSE
Requires-Dist: matplotlib
Requires-Dist: pandas
Requires-Dist: numpy
Requires-Dist: paho-mqtt
Requires-Dist: pathlib
Dynamic: license-file
